resume/__init__.py
resume/__main__.py
resume/_text/Luke_Garzia_Resume_202205.pdf
resume/_text/__init__.py
resume/_text/abridged.py
resume/_text/career_overview.py
resume/_text/contact.py
resume/_text/education.py
resume/_text/summary.py
resume/_text/technical_proficiencies.py
luke_resume-0.0.2.dist-info/entry_points.txt
luke_resume-0.0.2.dist-info/LICENSE
luke_resume-0.0.2.dist-info/WHEEL
luke_resume-0.0.2.dist-info/METADATA
luke_resume-0.0.2.dist-info/RECORD
