Metadata-Version: 2.1
Name: luke_resume
Version: 0.0.2
Summary: Luke Garzia's Resume CLI App - Making resumes fun since 2022 
Author-email: Luke Garzia <garzia.luke@gmail.com>
Requires-Python: >=3.7
Classifier: License :: OSI Approved :: MIT License
Requires-Dist: click >8.0.0
Requires-Dist: typer
Requires-Dist: sphinx ; extra == "doc"
Requires-Dist: myst-nb ; extra == "doc"
Requires-Dist: sphinx-rtd-theme ; extra == "doc"
Requires-Dist: sphinx-autoapi ; extra == "doc"
Requires-Dist: mypy ; extra == "test"
Requires-Dist: black ; extra == "test"
Requires-Dist: flake8 ; extra == "test"
Requires-Dist: isort ; extra == "test"
Requires-Dist: flake8-comprehensions ; extra == "test"
Requires-Dist: pre-commit ; extra == "test"
Requires-Dist: pytest ; extra == "test"
Requires-Dist: pytest-cov ; extra == "test"
Requires-Dist: interrogate ; extra == "test"
Requires-Dist: tox ; extra == "test"
Project-URL: Home, https://github.com/lgarzia/resume
Provides-Extra: doc
Provides-Extra: test
